crossplane/__init__.py
crossplane/__main__.py
crossplane/analyzer.py
crossplane/builder.py
crossplane/compat.py
crossplane/errors.py
crossplane/formatter.py
crossplane/lexer.py
crossplane/parse_to_json.py
crossplane/parser.py
crossplane/ext/__init__.py
crossplane/ext/abstract.py
crossplane/ext/lua.py
cscrossplane-0.5.5.dist-info/AUTHORS.rst
cscrossplane-0.5.5.dist-info/LICENSE
cscrossplane-0.5.5.dist-info/METADATA
cscrossplane-0.5.5.dist-info/NOTICE
cscrossplane-0.5.5.dist-info/WHEEL
cscrossplane-0.5.5.dist-info/entry_points.txt
cscrossplane-0.5.5.dist-info/top_level.txt
cscrossplane-0.5.5.dist-info/RECORD
